{
    "swagger": "2.0",
    "info": {
        "description": "Documentación de mi API Rest\n\nPara autenticarte:\n1. Usa el endpoint /auth/login para obtener el token\n2. Copia el token devuelto\n3. Click en el botón 'Authorize' (🔓) arriba\n4. Pega el token en el campo 'Value' (incluye 'Bearer ')",
        "title": "Viking-App ApiREST",
        "contact": {
            "name": "mirazopablo",
            "email": "mirazopablo@gmail.com"
        },
        "version": "1.0"
    },
    "host": "0.0.0.0:8080",
    "basePath": "/",
    "paths": {
        "/api/": {
            "get": {
                "security": [
                    {
                        "bearer-jwt": []
                    }
                ],
                "description": "Mensaje de bienvenida",
                "produces": [
                    "text/plain"
                ],
                "tags": [
                    "Home Controller"
                ],
                "summary": "Saludo",
                "operationId": "greeting",
                "responses": {
                    "200": {
                        "description": "OK",
                        "schema": {
                            "type": "string"
                        }
                    }
                }
            }
        },
        "/api/device/delete/{id}": {
            "delete": {
                "security": [
                    {
                        "bearer-jwt": []
                    }
                ],
                "description": "Elimina un dispositivo de la base de datos",
                "tags": [
                    "Device Controller"
                ],
                "summary": "Eliminar Dispositivo",
                "operationId": "deleteDevice",
                "parameters": [
                    {
                        "type": "string",
                        "format": "uuid",
                        "description": "Device UUID",
                        "name": "id",
                        "in": "path",
                        "required": true
                    }
                ],
                "responses": {
                    "200": {
                        "description": "OK"
                    }
                }
            }
        },
        "/api/device/save": {
            "post": {
                "security": [
                    {
                        "bearer-jwt": []
                    }
                ],
                "description": "Guarda un dispositivo en la base de datos",
                "consumes": [
                    "application/json"
                ],
                "produces": [
                    "application/json"
                ],
                "tags": [
                    "Device Controller"
                ],
                "summary": "Guardar Dispositivos",
                "operationId": "registerDevice",
                "parameters": [
                    {
                        "description": "Device Create Request",
                        "name": "device",
                        "in": "body",
                        "required": true,
                        "schema": {
                            "$ref": "#/definitions/models.DeviceCreateRequestDto"
                        }
                    }
                ],
                "responses": {
                    "200": {
                        "description": "OK",
                        "schema": {
                            "$ref": "#/definitions/models.DeviceResponseDto"
                        }
                    }
                }
            }
        },
        "/api/device/search": {
            "get": {
                "security": [
                    {
                        "bearer-jwt": []
                    }
                ],
                "description": "Busca dispositivos en la base de datos",
                "produces": [
                    "application/json"
                ],
                "tags": [
                    "Device Controller"
                ],
                "summary": "Buscar Dispositivos",
                "operationId": "searchDevice",
                "parameters": [
                    {
                        "type": "string",
                        "format": "uuid",
                        "description": "Device UUID",
                        "name": "id",
                        "in": "query"
                    },
                    {
                        "type": "string",
                        "description": "Serial Number",
                        "name": "serialNumber",
                        "in": "query"
                    },
                    {
                        "type": "string",
                        "description": "Brand",
                        "name": "brand",
                        "in": "query"
                    },
                    {
                        "type": "string",
                        "description": "User DNI (búsqueda parcial incremental)",
                        "name": "userDni",
                        "in": "query"
                    },
                    {
                        "type": "string",
                        "description": "User Name (búsqueda parcial incremental)",
                        "name": "userName",
                        "in": "query"
                    },
                    {
                        "type": "string",
                        "description": "Selector de campo o término general",
                        "name": "query",
                        "in": "query"
                    }
                ],
                "responses": {
                    "200": {
                        "description": "OK",
                        "schema": {
                            "type": "array",
                            "items": {
                                "$ref": "#/definitions/models.DeviceResponseDto"
                            }
                        }
                    }
                }
            }
        },
        "/api/device/update/{id}": {
            "patch": {
                "security": [
                    {
                        "bearer-jwt": []
                    }
                ],
                "description": "Actualiza un dispositivo existente de forma parcial o total",
                "consumes": [
                    "application/json"
                ],
                "produces": [
                    "application/json"
                ],
                "tags": [
                    "Device Controller"
                ],
                "summary": "Actualizar Dispositivo (Soporta PATCH parcial para reasignación de dueño)",
                "operationId": "updateDevice",
                "parameters": [
                    {
                        "type": "string",
                        "format": "uuid",
                        "description": "Device UUID",
                        "name": "id",
                        "in": "path",
                        "required": true
                    },
                    {
                        "description": "Device Update Request",
                        "name": "device",
                        "in": "body",
                        "required": true,
                        "schema": {
                            "$ref": "#/definitions/models.DeviceUpdateRequestDto"
                        }
                    }
                ],
                "responses": {
                    "200": {
                        "description": "OK",
                        "schema": {
                            "$ref": "#/definitions/models.DeviceResponseDto"
                        }
                    }
                }
            }
        },
        "/api/diagnostic-points/add": {
            "post": {
                "security": [
                    {
                        "bearer-jwt": []
                    }
                ],
                "description": "Agrega un nuevo punto de diagnóstico a una orden de trabajo",
                "consumes": [
                    "multipart/form-data"
                ],
                "produces": [
                    "application/json"
                ],
                "tags": [
                    "DiagnosticPoint"
                ],
                "summary": "Agregar punto de diagnóstico",
                "operationId": "addDiagnosticPoint",
                "parameters": [
                    {
                        "type": "string",
                        "description": "Work Order UUID",
                        "name": "workOrderId",
                        "in": "formData"
                    },
                    {
                        "type": "string",
                        "description": "Client UUID",
                        "name": "clientId",
                        "in": "formData"
                    },
                    {
                        "type": "string",
                        "description": "Diagnostic description or JSON string",
                        "name": "diagnosticPoint",
                        "in": "formData",
                        "required": true
                    },
                    {
                        "type": "file",
                        "description": "Attached image file",
                        "name": "file",
                        "in": "formData",
                        "required": true
                    }
                ],
                "responses": {
                    "200": {
                        "description": "OK",
                        "schema": {
                            "$ref": "#/definitions/models.DiagnosticPointResponseDto"
                        }
                    }
                }
            }
        },
        "/api/diagnostic-points/by-work-order/{workOrderId}": {
            "get": {
                "security": [
                    {
                        "bearer-jwt": []
                    }
                ],
                "description": "Obtiene una lista de puntos de diagnóstico por ID de orden de trabajo sin acoplamiento a clientId",
                "produces": [
                    "application/json"
                ],
                "tags": [
                    "DiagnosticPoint"
                ],
                "summary": "Obtener puntos de diagnóstico por ID de orden de trabajo",
                "operationId": "getDiagnosticPointsByWorkOrder",
                "parameters": [
                    {
                        "type": "string",
                        "format": "uuid",
                        "description": "Work Order UUID",
                        "name": "workOrderId",
                        "in": "path",
                        "required": true
                    }
                ],
                "responses": {
                    "200": {
                        "description": "OK",
                        "schema": {
                            "type": "array",
                            "items": {
                                "$ref": "#/definitions/models.DiagnosticPointResponseDto"
                            }
                        }
                    }
                }
            }
        },
        "/api/diagnostic-points/by-work-order/{workOrderId}/client/{clientId}": {
            "get": {
                "security": [
                    {
                        "bearer-jwt": []
                    }
                ],
                "description": "Obtiene una lista de puntos de diagnóstico por ID de orden de trabajo y Cliente Asociado a la orden de trabajo",
                "produces": [
                    "application/json"
                ],
                "tags": [
                    "DiagnosticPoint"
                ],
                "summary": "Obtener puntos de diagnóstico por ID de orden de trabajo",
                "operationId": "getDiagnosticPointsByWorkOrderAndClient",
                "parameters": [
                    {
                        "type": "string",
                        "format": "uuid",
                        "description": "Work Order UUID",
                        "name": "workOrderId",
                        "in": "path",
                        "required": true
                    },
                    {
                        "type": "string",
                        "format": "uuid",
                        "description": "Client UUID",
                        "name": "clientId",
                        "in": "path",
                        "required": true
                    }
                ],
                "responses": {
                    "200": {
                        "description": "OK",
                        "schema": {
                            "type": "array",
                            "items": {
                                "$ref": "#/definitions/models.DiagnosticPointResponseDto"
                            }
                        }
                    }
                }
            }
        },
        "/api/diagnostic-points/delete/{id}": {
            "delete": {
                "security": [
                    {
                        "bearer-jwt": []
                    }
                ],
                "description": "Borra una evidencia multimedia por UUID",
                "tags": [
                    "DiagnosticPoint"
                ],
                "summary": "Eliminar Punto de Diagnóstico",
                "operationId": "deleteDiagnosticPoint",
                "parameters": [
                    {
                        "type": "string",
                        "format": "uuid",
                        "description": "Diagnostic Point UUID",
                        "name": "id",
                        "in": "path",
                        "required": true
                    }
                ],
                "responses": {
                    "200": {
                        "description": "OK"
                    }
                }
            }
        },
        "/api/user-roles/is-staff": {
            "get": {
                "security": [
                    {
                        "bearer-jwt": []
                    }
                ],
                "description": "Verifica si el usuario es staff",
                "produces": [
                    "application/json"
                ],
                "tags": [
                    "User Role Controller"
                ],
                "summary": "Verificar si el usuario es staff",
                "operationId": "isUserStaff",
                "responses": {
                    "200": {
                        "description": "OK",
                        "schema": {
                            "type": "boolean"
                        }
                    }
                }
            }
        },
        "/api/user-roles/user-permission": {
            "get": {
                "security": [
                    {
                        "bearer-jwt": []
                    }
                ],
                "description": "Verifica si el usuario es admin",
                "produces": [
                    "application/json"
                ],
                "tags": [
                    "User Role Controller"
                ],
                "summary": "Verificar si el usuario es admin",
                "operationId": "getUserPermission",
                "responses": {
                    "200": {
                        "description": "OK",
                        "schema": {
                            "type": "string"
                        }
                    }
                }
            }
        },
        "/api/user/autocomplete": {
            "get": {
                "security": [
                    {
                        "bearer-jwt": []
                    }
                ],
                "description": "Devuelve una proyección ligera de usuarios para selectores sin exponer PII sensible",
                "produces": [
                    "application/json"
                ],
                "tags": [
                    "User Controller"
                ],
                "summary": "Autocompletado Rápido de Usuario / Cliente",
                "operationId": "autocompleteUser",
                "parameters": [
                    {
                        "type": "string",
                        "description": "Término de búsqueda (nombre, DNI o teléfono)",
                        "name": "query",
                        "in": "query"
                    }
                ],
                "responses": {
                    "200": {
                        "description": "OK",
                        "schema": {
                            "type": "array",
                            "items": {
                                "$ref": "#/definitions/models.UserAutocompleteDto"
                            }
                        }
                    }
                }
            }
        },
        "/api/user/current": {
            "get": {
                "security": [
                    {
                        "bearer-jwt": []
                    }
                ],
                "description": "Obtiene la información del usuario autenticado vía JWT en cabecera Authorization",
                "produces": [
                    "application/json"
                ],
                "tags": [
                    "User Controller"
                ],
                "summary": "Obtener Usuario Actual",
                "operationId": "getCurrentUser",
                "responses": {
                    "200": {
                        "description": "OK",
                        "schema": {
                            "$ref": "#/definitions/models.UserResponseDto"
                        }
                    }
                }
            }
        },
        "/api/user/delete/{id}": {
            "delete": {
                "security": [
                    {
                        "bearer-jwt": []
                    }
                ],
                "description": "Elimina un usuario existente",
                "tags": [
                    "User Controller"
                ],
                "summary": "Eliminar Usuario",
                "operationId": "deleteUser",
                "parameters": [
                    {
                        "type": "string",
                        "format": "uuid",
                        "description": "User UUID",
                        "name": "id",
                        "in": "path",
                        "required": true
                    }
                ],
                "responses": {
                    "200": {
                        "description": "OK"
                    }
                }
            }
        },
        "/api/user/save": {
            "post": {
                "security": [
                    {
                        "bearer-jwt": []
                    }
                ],
                "description": "Guarda un nuevo usuario en la base de datos",
                "consumes": [
                    "application/json"
                ],
                "produces": [
                    "application/json"
                ],
                "tags": [
                    "User Controller"
                ],
                "summary": "Guardar Usuario",
                "operationId": "registerUser_1",
                "parameters": [
                    {
                        "description": "User Create Request",
                        "name": "user",
                        "in": "body",
                        "required": true,
                        "schema": {
                            "$ref": "#/definitions/models.RegisterDto"
                        }
                    }
                ],
                "responses": {
                    "200": {
                        "description": "OK",
                        "schema": {
                            "type": "string"
                        }
                    }
                }
            }
        },
        "/api/user/search": {
            "get": {
                "security": [
                    {
                        "bearer-jwt": []
                    }
                ],
                "description": "Busca un usuario en la base de datos por ID o lista todos",
                "produces": [
                    "application/json"
                ],
                "tags": [
                    "User Controller"
                ],
                "summary": "Buscar Usuario",
                "operationId": "searchUser",
                "parameters": [
                    {
                        "type": "string",
                        "format": "uuid",
                        "description": "User UUID",
                        "name": "id",
                        "in": "query"
                    },
                    {
                        "type": "string",
                        "description": "User DNI (búsqueda parcial incremental)",
                        "name": "dni",
                        "in": "query"
                    },
                    {
                        "type": "string",
                        "description": "User Name",
                        "name": "name",
                        "in": "query"
                    },
                    {
                        "type": "string",
                        "description": "User Email",
                        "name": "email",
                        "in": "query"
                    },
                    {
                        "type": "string",
                        "description": "User Phone",
                        "name": "phone",
                        "in": "query"
                    },
                    {
                        "type": "string",
                        "description": "Selector de campo o término general",
                        "name": "query",
                        "in": "query"
                    }
                ],
                "responses": {
                    "200": {
                        "description": "OK",
                        "schema": {
                            "type": "array",
                            "items": {
                                "$ref": "#/definitions/models.UserResponseDto"
                            }
                        }
                    }
                }
            }
        },
        "/api/user/update/{id}": {
            "patch": {
                "security": [
                    {
                        "bearer-jwt": []
                    }
                ],
                "description": "Actualiza un usuario existente",
                "consumes": [
                    "application/json"
                ],
                "produces": [
                    "application/json"
                ],
                "tags": [
                    "User Controller"
                ],
                "summary": "Actualizar Usuario",
                "operationId": "updateUser",
                "parameters": [
                    {
                        "type": "string",
                        "format": "uuid",
                        "description": "User UUID",
                        "name": "id",
                        "in": "path",
                        "required": true
                    },
                    {
                        "description": "User Update Request",
                        "name": "user",
                        "in": "body",
                        "required": true,
                        "schema": {
                            "$ref": "#/definitions/models.RegisterDto"
                        }
                    }
                ],
                "responses": {
                    "200": {
                        "description": "OK",
                        "schema": {
                            "$ref": "#/definitions/models.UserResponseDto"
                        }
                    }
                }
            }
        },
        "/api/work-order/delete/{orderId}": {
            "delete": {
                "security": [
                    {
                        "bearer-jwt": []
                    }
                ],
                "description": "Borra o cancela una orden de trabajo por UUID",
                "tags": [
                    "Work Order Controller"
                ],
                "summary": "Eliminar Orden de Trabajo",
                "operationId": "deleteWorkOrder",
                "parameters": [
                    {
                        "type": "string",
                        "format": "uuid",
                        "description": "Work Order UUID",
                        "name": "orderId",
                        "in": "path",
                        "required": true
                    }
                ],
                "responses": {
                    "200": {
                        "description": "OK"
                    }
                }
            }
        },
        "/api/work-order/regenerate-code/{orderId}": {
            "patch": {
                "security": [
                    {
                        "bearer-jwt": []
                    }
                ],
                "description": "Genera un nuevo código de seguridad inyectado en DTO y revoca el anterior (solo hash en BD)",
                "produces": [
                    "application/json"
                ],
                "tags": [
                    "Work Order Controller"
                ],
                "summary": "Regenerar Código de Seguridad de Orden de Trabajo",
                "operationId": "regenerateSecurityCode",
                "parameters": [
                    {
                        "type": "string",
                        "format": "uuid",
                        "description": "Work Order UUID",
                        "name": "orderId",
                        "in": "path",
                        "required": true
                    }
                ],
                "responses": {
                    "200": {
                        "description": "OK",
                        "schema": {
                            "$ref": "#/definitions/models.SecurityCodeResponseDto"
                        }
                    }
                }
            }
        },
        "/api/work-order/save": {
            "post": {
                "security": [
                    {
                        "bearer-jwt": []
                    }
                ],
                "description": "Genera una nueva orden uniendo clientId, deviceId, descripción del problema y estado inicial",
                "consumes": [
                    "application/json"
                ],
                "produces": [
                    "application/json"
                ],
                "tags": [
                    "Work Order Controller"
                ],
                "summary": "Crear Orden de Trabajo",
                "operationId": "saveWorkOrder",
                "parameters": [
                    {
                        "description": "Work Order Create Request",
                        "name": "workOrder",
                        "in": "body",
                        "required": true,
                        "schema": {
                            "$ref": "#/definitions/models.WorkOrderCreateRequest"
                        }
                    }
                ],
                "responses": {
                    "200": {
                        "description": "OK",
                        "schema": {
                            "$ref": "#/definitions/models.WorkOrderResponseDto"
                        }
                    }
                }
            }
        },
        "/api/work-order/search": {
            "get": {
                "security": [
                    {
                        "bearer-jwt": []
                    }
                ],
                "description": "Permite rastrear reparaciones por staffId, clientDni, deviceSerialNumber o término general",
                "produces": [
                    "application/json"
                ],
                "tags": [
                    "Work Order Controller"
                ],
                "summary": "Buscar Órdenes de Trabajo",
                "operationId": "searchWorkOrder",
                "parameters": [
                    {
                        "type": "string",
                        "format": "uuid",
                        "description": "Staff UUID",
                        "name": "staffId",
                        "in": "query"
                    },
                    {
                        "type": "string",
                        "description": "Client DNI (búsqueda parcial incremental)",
                        "name": "clientDni",
                        "in": "query"
                    },
                    {
                        "type": "string",
                        "description": "Device Serial Number",
                        "name": "deviceSerialNumber",
                        "in": "query"
                    },
                    {
                        "type": "string",
                        "description": "Selector de campo o término general",
                        "name": "query",
                        "in": "query"
                    }
                ],
                "responses": {
                    "200": {
                        "description": "OK",
                        "schema": {
                            "type": "array",
                            "items": {
                                "$ref": "#/definitions/models.WorkOrderSummaryDto"
                            }
                        }
                    }
                }
            }
        },
        "/api/work-order/update/{orderId}": {
            "patch": {
                "security": [
                    {
                        "bearer-jwt": []
                    }
                ],
                "description": "Cambia el estado de reparación de una orden (RECEIVED -\u003e IN_PROGRESS -\u003e DONE)",
                "consumes": [
                    "application/json"
                ],
                "produces": [
                    "application/json"
                ],
                "tags": [
                    "Work Order Controller"
                ],
                "summary": "Actualizar Estado de Orden de Trabajo",
                "operationId": "updateWorkOrderStatus",
                "parameters": [
                    {
                        "type": "string",
                        "format": "uuid",
                        "description": "Work Order UUID",
                        "name": "orderId",
                        "in": "path",
                        "required": true
                    },
                    {
                        "description": "Status Update Request",
                        "name": "status",
                        "in": "body",
                        "required": true,
                        "schema": {
                            "$ref": "#/definitions/models.WorkOrderStatusUpdateRequestDto"
                        }
                    }
                ],
                "responses": {
                    "200": {
                        "description": "OK",
                        "schema": {
                            "$ref": "#/definitions/models.WorkOrderResponseDto"
                        }
                    }
                }
            }
        },
        "/api/work-order/{orderId}": {
            "get": {
                "security": [
                    {
                        "bearer-jwt": []
                    }
                ],
                "description": "Retorna el detalle completo de una orden de trabajo individual por su UUID",
                "produces": [
                    "application/json"
                ],
                "tags": [
                    "Work Order Controller"
                ],
                "summary": "Obtener Orden de Trabajo por ID",
                "operationId": "getWorkOrderById",
                "parameters": [
                    {
                        "type": "string",
                        "format": "uuid",
                        "description": "Work Order UUID",
                        "name": "orderId",
                        "in": "path",
                        "required": true
                    }
                ],
                "responses": {
                    "200": {
                        "description": "OK",
                        "schema": {
                            "$ref": "#/definitions/models.WorkOrderResponseDto"
                        }
                    }
                }
            }
        },
        "/auth/login": {
            "post": {
                "description": "Autentica a un usuario y retorna su token JWT",
                "consumes": [
                    "application/json"
                ],
                "produces": [
                    "application/json"
                ],
                "tags": [
                    "Auth"
                ],
                "summary": "Iniciar Sesión",
                "operationId": "authenticateUser",
                "parameters": [
                    {
                        "description": "Login Credentials",
                        "name": "creds",
                        "in": "body",
                        "required": true,
                        "schema": {
                            "$ref": "#/definitions/models.LoginUserDto"
                        }
                    }
                ],
                "responses": {
                    "200": {
                        "description": "OK",
                        "schema": {
                            "type": "object",
                            "additionalProperties": {
                                "type": "string"
                            }
                        }
                    }
                }
            }
        },
        "/auth/roles": {
            "get": {
                "security": [
                    {
                        "bearer-jwt": []
                    }
                ],
                "description": "Retorna la lista completa de roles disponibles en el sistema",
                "produces": [
                    "application/json"
                ],
                "tags": [
                    "Role Controller"
                ],
                "summary": "Listar Roles",
                "operationId": "getAllRoles",
                "responses": {
                    "200": {
                        "description": "OK",
                        "schema": {
                            "type": "array",
                            "items": {
                                "$ref": "#/definitions/models.Role"
                            }
                        }
                    }
                }
            },
            "post": {
                "security": [
                    {
                        "bearer-jwt": []
                    }
                ],
                "description": "Crea un nuevo rol",
                "consumes": [
                    "application/json"
                ],
                "produces": [
                    "application/json"
                ],
                "tags": [
                    "Role Controller"
                ],
                "summary": "Crear Rol",
                "operationId": "createRole",
                "parameters": [
                    {
                        "description": "Role Create Request",
                        "name": "role",
                        "in": "body",
                        "required": true,
                        "schema": {
                            "$ref": "#/definitions/models.RoleCreateRequest"
                        }
                    }
                ],
                "responses": {
                    "200": {
                        "description": "OK",
                        "schema": {
                            "$ref": "#/definitions/models.Role"
                        }
                    }
                }
            }
        },
        "/auth/roles/{id}": {
            "get": {
                "security": [
                    {
                        "bearer-jwt": []
                    }
                ],
                "description": "Busca un rol en la base de datos",
                "produces": [
                    "application/json"
                ],
                "tags": [
                    "Role Controller"
                ],
                "summary": "Buscar Rol",
                "operationId": "getRoleById",
                "parameters": [
                    {
                        "type": "string",
                        "format": "uuid",
                        "description": "Role UUID",
                        "name": "id",
                        "in": "path",
                        "required": true
                    }
                ],
                "responses": {
                    "200": {
                        "description": "OK",
                        "schema": {
                            "$ref": "#/definitions/models.Role"
                        }
                    }
                }
            },
            "put": {
                "security": [
                    {
                        "bearer-jwt": []
                    }
                ],
                "description": "Actualiza un rol existente",
                "consumes": [
                    "application/json"
                ],
                "produces": [
                    "application/json"
                ],
                "tags": [
                    "Role Controller"
                ],
                "summary": "Actualizar Rol",
                "operationId": "updateRole",
                "parameters": [
                    {
                        "type": "string",
                        "format": "uuid",
                        "description": "Role UUID",
                        "name": "id",
                        "in": "path",
                        "required": true
                    },
                    {
                        "description": "Role Update Request",
                        "name": "role",
                        "in": "body",
                        "required": true,
                        "schema": {
                            "$ref": "#/definitions/models.RoleCreateRequest"
                        }
                    }
                ],
                "responses": {
                    "200": {
                        "description": "OK",
                        "schema": {
                            "$ref": "#/definitions/models.Role"
                        }
                    }
                }
            },
            "delete": {
                "security": [
                    {
                        "bearer-jwt": []
                    }
                ],
                "description": "Elimina un rol existente",
                "tags": [
                    "Role Controller"
                ],
                "summary": "Eliminar Rol",
                "operationId": "deleteRole",
                "parameters": [
                    {
                        "type": "string",
                        "format": "uuid",
                        "description": "Role UUID",
                        "name": "id",
                        "in": "path",
                        "required": true
                    }
                ],
                "responses": {
                    "200": {
                        "description": "OK"
                    }
                }
            }
        },
        "/auth/signup": {
            "post": {
                "security": [
                    {
                        "bearer-jwt": []
                    }
                ],
                "description": "Crea y registra un nuevo usuario en la base de datos",
                "consumes": [
                    "application/json"
                ],
                "produces": [
                    "application/json"
                ],
                "tags": [
                    "Auth"
                ],
                "summary": "Registrar Usuario",
                "operationId": "registerUser",
                "parameters": [
                    {
                        "description": "Register Request",
                        "name": "user",
                        "in": "body",
                        "required": true,
                        "schema": {
                            "$ref": "#/definitions/models.RegisterDto"
                        }
                    }
                ],
                "responses": {
                    "200": {
                        "description": "OK",
                        "schema": {
                            "type": "string"
                        }
                    }
                }
            }
        },
        "/auth/uploads/{filepath}": {
            "get": {
                "description": "Carga un archivo o imagen desde el servidor (incluso en subcarpetas)",
                "produces": [
                    "application/octet-stream"
                ],
                "tags": [
                    "File Controller"
                ],
                "summary": "Cargar archivo",
                "operationId": "serveFile",
                "parameters": [
                    {
                        "type": "string",
                        "description": "Ruta relativa del archivo",
                        "name": "filepath",
                        "in": "path",
                        "required": true
                    }
                ],
                "responses": {
                    "200": {
                        "description": "OK",
                        "schema": {
                            "type": "file"
                        }
                    }
                }
            }
        },
        "/auth/validate": {
            "get": {
                "description": "Verifica si un token JWT enviado en la cabecera Authorization es válido",
                "produces": [
                    "application/json"
                ],
                "tags": [
                    "Auth"
                ],
                "summary": "Validar Token JWT",
                "operationId": "validateToken",
                "responses": {
                    "200": {
                        "description": "OK",
                        "schema": {
                            "type": "boolean"
                        }
                    }
                }
            }
        },
        "/public/notifications/history": {
            "get": {
                "description": "Permite la sincronización matutina (pull sync) al encender el servidor y actualiza la campanita interna",
                "produces": [
                    "application/json"
                ],
                "tags": [
                    "Notification Controller"
                ],
                "summary": "Obtener Historial de Notificaciones por Orden de Trabajo",
                "operationId": "getNotificationHistory",
                "parameters": [
                    {
                        "type": "string",
                        "format": "uuid",
                        "description": "Work Order UUID",
                        "name": "workOrderId",
                        "in": "query",
                        "required": true
                    },
                    {
                        "type": "string",
                        "description": "Security Code",
                        "name": "securityCode",
                        "in": "query",
                        "required": true
                    }
                ],
                "responses": {
                    "200": {
                        "description": "OK",
                        "schema": {
                            "type": "array",
                            "items": {
                                "$ref": "#/definitions/models.NotificationHistoryResponseDto"
                            }
                        }
                    },
                    "401": {
                        "description": "Unauthorized",
                        "schema": {
                            "type": "object",
                            "additionalProperties": {
                                "type": "string"
                            }
                        }
                    },
                    "404": {
                        "description": "Not Found",
                        "schema": {
                            "type": "object",
                            "additionalProperties": {
                                "type": "string"
                            }
                        }
                    }
                }
            }
        },
        "/public/notifications/mark-read": {
            "post": {
                "description": "Actualiza el estado de las alertas en la base de datos a leídas para el contador de la campanita",
                "consumes": [
                    "application/json"
                ],
                "produces": [
                    "application/json"
                ],
                "tags": [
                    "Notification Controller"
                ],
                "summary": "Marcar Todas las Notificaciones de una Orden como Leídas",
                "operationId": "markNotificationHistoryAsRead",
                "parameters": [
                    {
                        "type": "string",
                        "format": "uuid",
                        "description": "Work Order UUID",
                        "name": "workOrderId",
                        "in": "query",
                        "required": true
                    },
                    {
                        "type": "string",
                        "description": "Security Code",
                        "name": "securityCode",
                        "in": "query",
                        "required": true
                    }
                ],
                "responses": {
                    "200": {
                        "description": "OK",
                        "schema": {
                            "type": "object",
                            "additionalProperties": {
                                "type": "string"
                            }
                        }
                    },
                    "401": {
                        "description": "Unauthorized",
                        "schema": {
                            "type": "object",
                            "additionalProperties": {
                                "type": "string"
                            }
                        }
                    },
                    "404": {
                        "description": "Not Found",
                        "schema": {
                            "type": "object",
                            "additionalProperties": {
                                "type": "string"
                            }
                        }
                    }
                }
            }
        },
        "/public/notifications/subscribe": {
            "post": {
                "description": "Registra el endpoint y claves de cifrado del navegador para alertas en tiempo real de una orden",
                "consumes": [
                    "application/json"
                ],
                "produces": [
                    "application/json"
                ],
                "tags": [
                    "Notification Controller"
                ],
                "summary": "Suscribir Navegador a Notificaciones WebPush",
                "operationId": "subscribePushNotification",
                "parameters": [
                    {
                        "description": "Push Subscription Request",
                        "name": "subscription",
                        "in": "body",
                        "required": true,
                        "schema": {
                            "$ref": "#/definitions/models.PushSubscriptionCreateRequestDto"
                        }
                    }
                ],
                "responses": {
                    "200": {
                        "description": "OK",
                        "schema": {
                            "$ref": "#/definitions/models.PushSubscription"
                        }
                    },
                    "401": {
                        "description": "Unauthorized",
                        "schema": {
                            "type": "object",
                            "additionalProperties": {
                                "type": "string"
                            }
                        }
                    },
                    "404": {
                        "description": "Not Found",
                        "schema": {
                            "type": "object",
                            "additionalProperties": {
                                "type": "string"
                            }
                        }
                    }
                }
            }
        },
        "/public/notifications/unsubscribe": {
            "post": {
                "description": "Revoca o elimina la suscripción WebPush utilizando la URL del endpoint",
                "consumes": [
                    "application/json"
                ],
                "produces": [
                    "application/json"
                ],
                "tags": [
                    "Notification Controller"
                ],
                "summary": "Desuscribir Navegador de Notificaciones WebPush",
                "operationId": "unsubscribePushNotification",
                "parameters": [
                    {
                        "description": "Unsubscribe Request",
                        "name": "request",
                        "in": "body",
                        "required": true,
                        "schema": {
                            "$ref": "#/definitions/models.PushSubscriptionUnsubscribeRequestDto"
                        }
                    }
                ],
                "responses": {
                    "200": {
                        "description": "OK",
                        "schema": {
                            "type": "object",
                            "additionalProperties": {
                                "type": "string"
                            }
                        }
                    }
                }
            }
        },
        "/public/work-order/status": {
            "post": {
                "description": "Devuelve el estado, detalles y puntos de diagnóstico de una orden de trabajo si el id y securityCode coinciden",
                "consumes": [
                    "application/json"
                ],
                "produces": [
                    "application/json"
                ],
                "tags": [
                    "Work Order Controller"
                ],
                "summary": "Consulta Pública de Orden de Trabajo",
                "operationId": "getPublicStatus",
                "parameters": [
                    {
                        "description": "Public Query Request",
                        "name": "query",
                        "in": "body",
                        "required": true,
                        "schema": {
                            "$ref": "#/definitions/models.WorkOrderPublicQueryRequestDto"
                        }
                    }
                ],
                "responses": {
                    "200": {
                        "description": "OK",
                        "schema": {
                            "$ref": "#/definitions/models.WorkOrderPublicStatusResponseDto"
                        }
                    },
                    "401": {
                        "description": "Unauthorized",
                        "schema": {
                            "type": "object",
                            "additionalProperties": {
                                "type": "string"
                            }
                        }
                    },
                    "404": {
                        "description": "Not Found",
                        "schema": {
                            "type": "object",
                            "additionalProperties": {
                                "type": "string"
                            }
                        }
                    }
                }
            }
        },
        "/public/work-order/status-by-dni": {
            "post": {
                "description": "Devuelve el estado, detalles y puntos de diagnóstico de una orden de trabajo si el DNI del cliente y securityCode coinciden",
                "consumes": [
                    "application/json"
                ],
                "produces": [
                    "application/json"
                ],
                "tags": [
                    "Work Order Controller"
                ],
                "summary": "Consulta Pública de Orden de Trabajo por DNI",
                "operationId": "getPublicStatusByDni",
                "parameters": [
                    {
                        "description": "Public DNI Query Request",
                        "name": "query",
                        "in": "body",
                        "required": true,
                        "schema": {
                            "$ref": "#/definitions/models.WorkOrderPublicDniQueryRequestDto"
                        }
                    }
                ],
                "responses": {
                    "200": {
                        "description": "OK",
                        "schema": {
                            "$ref": "#/definitions/models.WorkOrderPublicStatusResponseDto"
                        }
                    },
                    "401": {
                        "description": "Unauthorized",
                        "schema": {
                            "type": "object",
                            "additionalProperties": {
                                "type": "string"
                            }
                        }
                    },
                    "404": {
                        "description": "Not Found",
                        "schema": {
                            "type": "object",
                            "additionalProperties": {
                                "type": "string"
                            }
                        }
                    }
                }
            }
        }
    },
    "definitions": {
        "models.DeviceCreateRequestDto": {
            "type": "object",
            "required": [
                "brand",
                "model",
                "serialNumber",
                "type",
                "userId"
            ],
            "properties": {
                "brand": {
                    "type": "string"
                },
                "model": {
                    "type": "string"
                },
                "serialNumber": {
                    "type": "string"
                },
                "type": {
                    "type": "string"
                },
                "userId": {
                    "type": "string"
                }
            }
        },
        "models.DeviceResponseDto": {
            "type": "object",
            "properties": {
                "brand": {
                    "type": "string"
                },
                "id": {
                    "type": "string"
                },
                "model": {
                    "type": "string"
                },
                "serialNumber": {
                    "type": "string"
                },
                "type": {
                    "type": "string"
                },
                "userDni": {
                    "type": "integer"
                },
                "userId": {
                    "type": "string"
                },
                "userName": {
                    "type": "string"
                },
                "userPhone": {
                    "type": "string"
                }
            }
        },
        "models.DeviceUpdateRequestDto": {
            "type": "object",
            "properties": {
                "brand": {
                    "type": "string"
                },
                "id": {
                    "type": "string"
                },
                "model": {
                    "type": "string"
                },
                "serialNumber": {
                    "type": "string"
                },
                "type": {
                    "type": "string"
                },
                "userId": {
                    "type": "string"
                }
            }
        },
        "models.DiagnosticPointResponseDto": {
            "type": "object",
            "properties": {
                "clientId": {
                    "type": "string"
                },
                "createdAt": {
                    "type": "string"
                },
                "description": {
                    "type": "string"
                },
                "id": {
                    "type": "string"
                },
                "imageUrl": {
                    "type": "string"
                },
                "workOrderId": {
                    "type": "string"
                }
            }
        },
        "models.LoginUserDto": {
            "type": "object",
            "required": [
                "email",
                "password"
            ],
            "properties": {
                "email": {
                    "type": "string",
                    "example": "admin@viking.com"
                },
                "password": {
                    "type": "string",
                    "example": "secret123"
                }
            }
        },
        "models.NotificationHistoryResponseDto": {
            "type": "object",
            "properties": {
                "body": {
                    "type": "string"
                },
                "createdAt": {
                    "type": "string"
                },
                "id": {
                    "type": "string"
                },
                "isRead": {
                    "type": "boolean"
                },
                "targetUrl": {
                    "type": "string"
                },
                "title": {
                    "type": "string"
                },
                "type": {
                    "type": "string"
                }
            }
        },
        "models.PushSubscription": {
            "type": "object",
            "properties": {
                "auth": {
                    "type": "string"
                },
                "createdAt": {
                    "type": "string"
                },
                "endpoint": {
                    "type": "string"
                },
                "id": {
                    "type": "string"
                },
                "p256dh": {
                    "type": "string"
                },
                "updatedAt": {
                    "type": "string"
                },
                "userAgent": {
                    "type": "string"
                },
                "workOrderId": {
                    "type": "string"
                }
            }
        },
        "models.PushSubscriptionCreateRequestDto": {
            "type": "object",
            "required": [
                "endpoint",
                "keys",
                "securityCode",
                "workOrderId"
            ],
            "properties": {
                "endpoint": {
                    "type": "string"
                },
                "keys": {
                    "type": "object",
                    "required": [
                        "auth",
                        "p256dh"
                    ],
                    "properties": {
                        "auth": {
                            "type": "string"
                        },
                        "p256dh": {
                            "type": "string"
                        }
                    }
                },
                "securityCode": {
                    "type": "string"
                },
                "userAgent": {
                    "type": "string"
                },
                "workOrderId": {
                    "type": "string"
                }
            }
        },
        "models.PushSubscriptionUnsubscribeRequestDto": {
            "type": "object",
            "required": [
                "endpoint"
            ],
            "properties": {
                "endpoint": {
                    "type": "string"
                }
            }
        },
        "models.RegisterDto": {
            "type": "object",
            "required": [
                "address",
                "dni",
                "email",
                "name",
                "phoneNumber",
                "roleId"
            ],
            "properties": {
                "address": {
                    "type": "string",
                    "example": "Calle Valhalla 123"
                },
                "dni": {
                    "type": "integer",
                    "example": 30123456
                },
                "email": {
                    "type": "string",
                    "example": "admin@viking.com"
                },
                "name": {
                    "type": "string",
                    "maxLength": 150,
                    "minLength": 2,
                    "example": "Viking Admin"
                },
                "password": {
                    "type": "string",
                    "minLength": 6,
                    "example": "secret123"
                },
                "phoneNumber": {
                    "type": "string",
                    "example": "5491112345678"
                },
                "roleId": {
                    "type": "string",
                    "example": "123e4567-e89b-12d3-a456-426614174000"
                },
                "secondaryPhoneNumber": {
                    "type": "string",
                    "example": "5491187654321"
                }
            }
        },
        "models.Role": {
            "type": "object",
            "required": [
                "descripcion"
            ],
            "properties": {
                "descripcion": {
                    "type": "string",
                    "maxLength": 100,
                    "minLength": 2,
                    "example": "ADMIN"
                },
                "id": {
                    "type": "string",
                    "example": "123e4567-e89b-12d3-a456-426614174000"
                }
            }
        },
        "models.RoleCreateRequest": {
            "type": "object",
            "required": [
                "descripcion"
            ],
            "properties": {
                "descripcion": {
                    "type": "string",
                    "maxLength": 100,
                    "minLength": 2,
                    "example": "ADMIN"
                }
            }
        },
        "models.SecurityCodeResponseDto": {
            "type": "object",
            "properties": {
                "clientName": {
                    "type": "string"
                },
                "id": {
                    "type": "string"
                },
                "securityCode": {
                    "type": "string"
                }
            }
        },
        "models.UserAutocompleteDto": {
            "type": "object",
            "properties": {
                "dni": {
                    "type": "integer",
                    "example": 30123456
                },
                "id": {
                    "type": "string",
                    "example": "123e4567-e89b-12d3-a456-426614174000"
                },
                "name": {
                    "type": "string",
                    "example": "Viking Admin"
                },
                "phoneNumber": {
                    "type": "string",
                    "example": "5491112345678"
                }
            }
        },
        "models.UserResponseDto": {
            "type": "object",
            "properties": {
                "address": {
                    "type": "string",
                    "example": "Calle Valhalla 123"
                },
                "dni": {
                    "type": "integer",
                    "example": 30123456
                },
                "email": {
                    "type": "string",
                    "example": "admin@viking.com"
                },
                "id": {
                    "type": "string",
                    "example": "123e4567-e89b-12d3-a456-426614174000"
                },
                "name": {
                    "type": "string",
                    "example": "Viking Admin"
                },
                "phoneNumber": {
                    "type": "string",
                    "example": "5491112345678"
                },
                "roleId": {
                    "type": "string",
                    "example": "123e4567-e89b-12d3-a456-426614174000"
                },
                "secondaryPhoneNumber": {
                    "type": "string",
                    "example": "5491187654321"
                }
            }
        },
        "models.WorkOrderCreateRequest": {
            "type": "object",
            "required": [
                "clientId",
                "deviceId",
                "issueDescription",
                "repairStatus"
            ],
            "properties": {
                "clientId": {
                    "type": "string"
                },
                "deviceId": {
                    "type": "string"
                },
                "issueDescription": {
                    "type": "string",
                    "maxLength": 200,
                    "minLength": 2
                },
                "notes": {
                    "type": "string"
                },
                "repairStatus": {
                    "type": "string"
                }
            }
        },
        "models.WorkOrderPublicDniQueryRequestDto": {
            "type": "object",
            "required": [
                "clientDni",
                "securityCode"
            ],
            "properties": {
                "clientDni": {
                    "type": "integer"
                },
                "securityCode": {
                    "type": "string"
                }
            }
        },
        "models.WorkOrderPublicQueryRequestDto": {
            "type": "object",
            "required": [
                "id",
                "securityCode"
            ],
            "properties": {
                "id": {
                    "type": "string"
                },
                "securityCode": {
                    "type": "string"
                }
            }
        },
        "models.WorkOrderPublicStatusResponseDto": {
            "type": "object",
            "properties": {
                "diagnosticPoints": {
                    "type": "array",
                    "items": {
                        "$ref": "#/definitions/models.DiagnosticPointResponseDto"
                    }
                },
                "workOrder": {
                    "$ref": "#/definitions/models.WorkOrderResponseDto"
                }
            }
        },
        "models.WorkOrderResponseDto": {
            "type": "object",
            "properties": {
                "clientDni": {
                    "type": "integer"
                },
                "clientId": {
                    "type": "string"
                },
                "clientName": {
                    "type": "string"
                },
                "clientPhone": {
                    "type": "string"
                },
                "createdAt": {
                    "type": "string"
                },
                "deviceBrand": {
                    "type": "string"
                },
                "deviceId": {
                    "type": "string"
                },
                "deviceModel": {
                    "type": "string"
                },
                "deviceSerialNumber": {
                    "type": "string"
                },
                "id": {
                    "type": "string"
                },
                "issueDescription": {
                    "type": "string"
                },
                "notes": {
                    "type": "string"
                },
                "repairStatus": {
                    "type": "string"
                },
                "securityCode": {
                    "type": "string"
                },
                "staffId": {
                    "type": "string"
                },
                "staffName": {
                    "type": "string"
                },
                "updatedAt": {
                    "type": "string"
                }
            }
        },
        "models.WorkOrderStatusUpdateRequestDto": {
            "type": "object",
            "required": [
                "repairStatus"
            ],
            "properties": {
                "repairStatus": {
                    "type": "string"
                }
            }
        },
        "models.WorkOrderSummaryDto": {
            "type": "object",
            "properties": {
                "clientId": {
                    "type": "string"
                },
                "clientName": {
                    "type": "string"
                },
                "createdAt": {
                    "type": "string"
                },
                "deviceBrand": {
                    "type": "string"
                },
                "deviceId": {
                    "type": "string"
                },
                "deviceModel": {
                    "type": "string"
                },
                "id": {
                    "type": "string"
                },
                "issueDescription": {
                    "type": "string"
                },
                "repairStatus": {
                    "type": "string"
                },
                "securityCode": {
                    "type": "string"
                }
            }
        }
    },
    "securityDefinitions": {
        "bearer-jwt": {
            "type": "apiKey",
            "name": "Authorization",
            "in": "header"
        }
    }
}